ckan_downloader/__init__.py
ckan_downloader/__main__.py
ckan_downloader/_version.py
ckan_downloader-0.1.1.dist-info/WHEEL
ckan_downloader-0.1.1.dist-info/METADATA
ckan_downloader-0.1.1.dist-info/RECORD
