Metadata-Version: 2.1
Name: ckan-downloader
Version: 0.1.1
Summary: An interactive command-line utility for downloading data from a CKAN data portal
License: MIT
Author: Eric McCowan
Author-email: eric.mccowan@servian.com
Requires-Python: >=3,<4
Classifier: License :: OSI Approved :: MIT License
Classifier: Programming Language :: Python :: 3
Classifier: Programming Language :: Python :: 3.4
Classifier: Programming Language :: Python :: 3.5
Classifier: Programming Language :: Python :: 3.6
Classifier: Programming Language :: Python :: 3.7
Classifier: Programming Language :: Python :: 3.8
Classifier: Programming Language :: Python :: 3.9
Requires-Dist: requests (>=2.24.0,<3.0.0)
Requires-Dist: tqdm (>=4.51.0,<5.0.0)
